poly_apis/__init__.py
poly_apis/client.py
poly_apis/clob_types.old.py
poly_apis/clob_types.py
poly_apis/config.py
poly_apis/constants.py
poly_apis/endpoints.py
poly_apis/exceptions.old.py
poly_apis/exceptions.py
poly_apis/signer.py
poly_apis/utilities.py
poly_apis/headers/__init__.py
poly_apis/headers/headers.py
poly_apis/http_helpers/__init__.py
poly_apis/http_helpers/helpers.old.py
poly_apis/http_helpers/helpers.py
poly_apis/order_builder/__init__.py
poly_apis/order_builder/builder.py
poly_apis/order_builder/constants.py
poly_apis/order_builder/helpers.py
poly_apis/signing/__init__.py
poly_apis/signing/eip712.py
poly_apis/signing/hmac.py
poly_apis/signing/model.py
poly_apis-0.1.7.dist-info/METADATA
poly_apis-0.1.7.dist-info/WHEEL
poly_apis-0.1.7.dist-info/RECORD
